{
    "user_id": "orange3",
    "session_id": "5d154da481249f67dd06aaac",
    "study": "studyF",
    "workspace": "cane.cane-yellow",
    "details": {
        "workspace": "cane.cane-yellow",
        "labels": [
            {
                "time": 28.004519,
                "endTime": 29.628354,
                "type": "ground",
                "id": 1
            },
            {
                "time": 30.141513,
                "endTime": 31.463958,
                "type": "ground",
                "id": 2
            },
            {
                "time": 31.939348,
                "endTime": 32.948995,
                "type": "ground",
                "id": 3
            },
            {
                "time": 33.620409,
                "endTime": 34.848036,
                "type": "ground",
                "id": 4
            },
            {
                "time": 35.414995,
                "endTime": 36.486887,
                "type": "ground",
                "id": 5
            },
            {
                "time": 37.141563,
                "endTime": 38.482381,
                "type": "ground",
                "id": 6
            },
            {
                "time": 39.056275,
                "endTime": 40.180039,
                "type": "ground",
                "id": 7
            },
            {
                "time": 40.595515,
                "endTime": 41.591435,
                "type": "ground",
                "id": 8
            },
            {
                "time": 41.940311,
                "endTime": 43.989483,
                "type": "ground",
                "id": 9
            },
            {
                "time": 44.304553,
                "endTime": 45.769257,
                "type": "ground",
                "id": 10
            },
            {
                "time": 46.070296,
                "endTime": 47.440231,
                "type": "ground",
                "id": 11
            },
            {
                "time": 47.825527,
                "endTime": 49.03411,
                "type": "ground",
                "id": 12
            },
            {
                "time": 49.4925,
                "endTime": 50.690616,
                "type": "ground",
                "id": 13
            },
            {
                "time": 51.188599,
                "endTime": 54.130659,
                "type": "ground",
                "id": 14
            },
            {
                "time": 54.130659,
                "endTime": 55.396958,
                "type": "ground",
                "id": 15
            },
            {
                "time": 55.396958,
                "endTime": 55.67166,
                "type": "ground",
                "id": 16
            },
            {
                "time": 56.199855,
                "endTime": 56.709145,
                "type": "ground",
                "id": 17
            },
            {
                "time": 57.222235,
                "endTime": 58.335879,
                "type": "ground",
                "id": 18
            },
            {
                "time": 58.722312,
                "endTime": 59.98822,
                "type": "ground",
                "id": 19
            },
            {
                "time": 60.432021,
                "endTime": 61.701619,
                "type": "ground",
                "id": 20
            },
            {
                "time": 62.178391,
                "endTime": 63.556177,
                "type": "ground",
                "id": 21
            }
        ],
        "_starts": [
            "2019-06-27T23:19:36.000Z"
        ],
        "_ends": [
            "2019-06-27T23:21:10.129Z"
        ]
    },
    "labels_file": "/home/ubuntu/vat/data/user-studies/studyF/practice-third/orange3.labels.json",
    "videoFlash": 2.133995,
    "surveys": {
        "user-info": {
            "firstname": "Benjamin",
            "lastname": "Szamosfalvi",
            "email": "benszthehun@gmail.com"
        },
        "practice-first": {
            "question1": "5",
            "question2": "ok",
            "question3": "20",
            "question4": "3"
        },
        "practice-second": {}
    },
    "logs": {
        "labelEvents": [
            {
                "time": "2019-06-27T23:20:00.733Z",
                "type": "START",
                "source": "hotkey",
                "_t": "17:20:00",
                "_end": "-",
                "data": {
                    "type": "ground",
                    "time": 27.929959
                }
            },
            {
                "time": "2019-06-27T23:20:02.872Z",
                "type": "END",
                "source": "hotkey:ctb",
                "_t": "17:20:02",
                "_end": "-",
                "data": {
                    "lbl": {
                        "time": 27.929959,
                        "endTime": 30.064546,
                        "type": "ground",
                        "id": 1
                    },
                    "key": "enter"
                }
            },
            {
                "time": "2019-06-27T23:20:03.964Z",
                "type": "START",
                "source": "hotkey",
                "_t": "17:20:03",
                "_end": "-",
                "data": {
                    "type": "ground",
                    "time": 31.15373
                }
            },
            {
                "time": "2019-06-27T23:20:06.486Z",
                "type": "CANCEL",
                "source": "hotkey",
                "_t": "17:20:06",
                "_end": "-",
                "data": {
                    "time": 31.15373,
                    "type": "ground",
                    "editting": false
                }
            },
            {
                "time": "2019-06-27T23:20:14.939Z",
                "type": "SELECT",
                "source": "data:click",
                "_t": "17:20:14",
                "_end": "-",
                "data": {
                    "time": 27.929959,
                    "endTime": 30.064546,
                    "type": "ground",
                    "id": 1
                }
            },
            {
                "time": "2019-06-27T23:20:15.783Z",
                "type": "DELETE",
                "source": "hotkey",
                "_t": "17:20:15",
                "_end": "-",
                "data": {
                    "id": 1,
                    "idx": 0
                }
            },
            {
                "time": "2019-06-27T23:20:22.168Z",
                "type": "START",
                "source": "hotkey",
                "_t": "17:20:22",
                "_end": "-",
                "data": {
                    "type": "ground",
                    "time": 28.004519
                }
            },
            {
                "time": "2019-06-27T23:20:25.272Z",
                "type": "END",
                "source": "hotkey:ctb",
                "_t": "17:20:25",
                "_end": "-",
                "data": {
                    "lbl": {
                        "time": 28.004519,
                        "endTime": 29.628354,
                        "type": "ground",
                        "id": 1
                    },
                    "key": "enter"
                }
            },
            {
                "time": "2019-06-27T23:20:28.584Z",
                "type": "START",
                "source": "hotkey",
                "_t": "17:20:28",
                "_end": "-",
                "data": {
                    "type": "ground",
                    "time": 30.141513
                }
            },
            {
                "time": "2019-06-27T23:20:31.975Z",
                "type": "END",
                "source": "hotkey:ctb",
                "_t": "17:20:31",
                "_end": "-",
                "data": {
                    "lbl": {
                        "time": 30.141513,
                        "endTime": 31.463958,
                        "type": "ground",
                        "id": 2
                    },
                    "key": "enter"
                }
            },
            {
                "time": "2019-06-27T23:20:32.456Z",
                "type": "START",
                "source": "hotkey",
                "_t": "17:20:32",
                "_end": "-",
                "data": {
                    "type": "ground",
                    "time": 31.939348
                }
            },
            {
                "time": "2019-06-27T23:20:33.464Z",
                "type": "END",
                "source": "hotkey:ctb",
                "_t": "17:20:33",
                "_end": "-",
                "data": {
                    "lbl": {
                        "time": 31.939348,
                        "endTime": 32.948995,
                        "type": "ground",
                        "id": 3
                    },
                    "key": "enter"
                }
            },
            {
                "time": "2019-06-27T23:20:34.136Z",
                "type": "START",
                "source": "hotkey",
                "_t": "17:20:34",
                "_end": "-",
                "data": {
                    "type": "ground",
                    "time": 33.620409
                }
            },
            {
                "time": "2019-06-27T23:20:35.368Z",
                "type": "END",
                "source": "hotkey:ctb",
                "_t": "17:20:35",
                "_end": "-",
                "data": {
                    "lbl": {
                        "time": 33.620409,
                        "endTime": 34.848036,
                        "type": "ground",
                        "id": 4
                    },
                    "key": "enter"
                }
            },
            {
                "time": "2019-06-27T23:20:35.926Z",
                "type": "START",
                "source": "hotkey",
                "_t": "17:20:35",
                "_end": "-",
                "data": {
                    "type": "ground",
                    "time": 35.414995
                }
            },
            {
                "time": "2019-06-27T23:20:37.001Z",
                "type": "END",
                "source": "hotkey:ctb",
                "_t": "17:20:37",
                "_end": "-",
                "data": {
                    "lbl": {
                        "time": 35.414995,
                        "endTime": 36.486887,
                        "type": "ground",
                        "id": 5
                    },
                    "key": "enter"
                }
            },
            {
                "time": "2019-06-27T23:20:37.656Z",
                "type": "START",
                "source": "hotkey",
                "_t": "17:20:37",
                "_end": "-",
                "data": {
                    "type": "ground",
                    "time": 37.141563
                }
            },
            {
                "time": "2019-06-27T23:20:39.001Z",
                "type": "END",
                "source": "hotkey:ctb",
                "_t": "17:20:39",
                "_end": "-",
                "data": {
                    "lbl": {
                        "time": 37.141563,
                        "endTime": 38.482381,
                        "type": "ground",
                        "id": 6
                    },
                    "key": "enter"
                }
            },
            {
                "time": "2019-06-27T23:20:39.577Z",
                "type": "START",
                "source": "hotkey",
                "_t": "17:20:39",
                "_end": "-",
                "data": {
                    "type": "ground",
                    "time": 39.056275
                }
            },
            {
                "time": "2019-06-27T23:20:40.695Z",
                "type": "END",
                "source": "hotkey:ctb",
                "_t": "17:20:40",
                "_end": "-",
                "data": {
                    "lbl": {
                        "time": 39.056275,
                        "endTime": 40.180039,
                        "type": "ground",
                        "id": 7
                    },
                    "key": "enter"
                }
            },
            {
                "time": "2019-06-27T23:20:41.113Z",
                "type": "START",
                "source": "hotkey",
                "_t": "17:20:41",
                "_end": "-",
                "data": {
                    "type": "ground",
                    "time": 40.595515
                }
            },
            {
                "time": "2019-06-27T23:20:42.105Z",
                "type": "END",
                "source": "hotkey:ctb",
                "_t": "17:20:42",
                "_end": "-",
                "data": {
                    "lbl": {
                        "time": 40.595515,
                        "endTime": 41.591435,
                        "type": "ground",
                        "id": 8
                    },
                    "key": "enter"
                }
            },
            {
                "time": "2019-06-27T23:20:42.460Z",
                "type": "START",
                "source": "hotkey",
                "_t": "17:20:42",
                "_end": "-",
                "data": {
                    "type": "ground",
                    "time": 41.940311
                }
            },
            {
                "time": "2019-06-27T23:20:44.506Z",
                "type": "END",
                "source": "hotkey:ctb",
                "_t": "17:20:44",
                "_end": "-",
                "data": {
                    "lbl": {
                        "time": 41.940311,
                        "endTime": 43.989483,
                        "type": "ground",
                        "id": 9
                    },
                    "key": "enter"
                }
            },
            {
                "time": "2019-06-27T23:20:44.825Z",
                "type": "START",
                "source": "hotkey",
                "_t": "17:20:44",
                "_end": "-",
                "data": {
                    "type": "ground",
                    "time": 44.304553
                }
            },
            {
                "time": "2019-06-27T23:20:46.281Z",
                "type": "END",
                "source": "hotkey:ctb",
                "_t": "17:20:46",
                "_end": "-",
                "data": {
                    "lbl": {
                        "time": 44.304553,
                        "endTime": 45.769257,
                        "type": "ground",
                        "id": 10
                    },
                    "key": "enter"
                }
            },
            {
                "time": "2019-06-27T23:20:46.585Z",
                "type": "START",
                "source": "hotkey",
                "_t": "17:20:46",
                "_end": "-",
                "data": {
                    "type": "ground",
                    "time": 46.070296
                }
            },
            {
                "time": "2019-06-27T23:20:47.959Z",
                "type": "END",
                "source": "hotkey:ctb",
                "_t": "17:20:47",
                "_end": "-",
                "data": {
                    "lbl": {
                        "time": 46.070296,
                        "endTime": 47.440231,
                        "type": "ground",
                        "id": 11
                    },
                    "key": "enter"
                }
            },
            {
                "time": "2019-06-27T23:20:48.345Z",
                "type": "START",
                "source": "hotkey",
                "_t": "17:20:48",
                "_end": "-",
                "data": {
                    "type": "ground",
                    "time": 47.825527
                }
            },
            {
                "time": "2019-06-27T23:20:49.546Z",
                "type": "END",
                "source": "hotkey:ctb",
                "_t": "17:20:49",
                "_end": "-",
                "data": {
                    "lbl": {
                        "time": 47.825527,
                        "endTime": 49.03411,
                        "type": "ground",
                        "id": 12
                    },
                    "key": "enter"
                }
            },
            {
                "time": "2019-06-27T23:20:50.009Z",
                "type": "START",
                "source": "hotkey",
                "_t": "17:20:50",
                "_end": "-",
                "data": {
                    "type": "ground",
                    "time": 49.4925
                }
            },
            {
                "time": "2019-06-27T23:20:51.207Z",
                "type": "END",
                "source": "hotkey:ctb",
                "_t": "17:20:51",
                "_end": "-",
                "data": {
                    "lbl": {
                        "time": 49.4925,
                        "endTime": 50.690616,
                        "type": "ground",
                        "id": 13
                    },
                    "key": "enter"
                }
            },
            {
                "time": "2019-06-27T23:20:51.704Z",
                "type": "START",
                "source": "hotkey",
                "_t": "17:20:51",
                "_end": "-",
                "data": {
                    "type": "ground",
                    "time": 51.188599
                }
            },
            {
                "time": "2019-06-27T23:20:54.650Z",
                "type": "START",
                "source": "hotkey",
                "_t": "17:20:54",
                "_end": "-",
                "data": {
                    "type": "ground",
                    "time": 54.130659
                }
            },
            {
                "time": "2019-06-27T23:20:55.913Z",
                "type": "START",
                "source": "hotkey",
                "_t": "17:20:55",
                "_end": "-",
                "data": {
                    "type": "ground",
                    "time": 55.396958
                }
            },
            {
                "time": "2019-06-27T23:20:56.189Z",
                "type": "END",
                "source": "hotkey:ctb",
                "_t": "17:20:56",
                "_end": "-",
                "data": {
                    "lbl": {
                        "time": 55.396958,
                        "endTime": 55.67166,
                        "type": "ground",
                        "id": 16
                    },
                    "key": "enter"
                }
            },
            {
                "time": "2019-06-27T23:20:56.716Z",
                "type": "START",
                "source": "hotkey",
                "_t": "17:20:56",
                "_end": "-",
                "data": {
                    "type": "ground",
                    "time": 56.199855
                }
            },
            {
                "time": "2019-06-27T23:20:57.224Z",
                "type": "END",
                "source": "hotkey:ctb",
                "_t": "17:20:57",
                "_end": "-",
                "data": {
                    "lbl": {
                        "time": 56.199855,
                        "endTime": 56.709145,
                        "type": "ground",
                        "id": 17
                    },
                    "key": "enter"
                }
            },
            {
                "time": "2019-06-27T23:20:57.735Z",
                "type": "START",
                "source": "hotkey",
                "_t": "17:20:57",
                "_end": "-",
                "data": {
                    "type": "ground",
                    "time": 57.222235
                }
            },
            {
                "time": "2019-06-27T23:20:58.858Z",
                "type": "END",
                "source": "hotkey:ctb",
                "_t": "17:20:58",
                "_end": "-",
                "data": {
                    "lbl": {
                        "time": 57.222235,
                        "endTime": 58.335879,
                        "type": "ground",
                        "id": 18
                    },
                    "key": "enter"
                }
            },
            {
                "time": "2019-06-27T23:20:59.242Z",
                "type": "START",
                "source": "hotkey",
                "_t": "17:20:59",
                "_end": "-",
                "data": {
                    "type": "ground",
                    "time": 58.722312
                }
            },
            {
                "time": "2019-06-27T23:21:00.505Z",
                "type": "END",
                "source": "hotkey:ctb",
                "_t": "17:21:00",
                "_end": "-",
                "data": {
                    "lbl": {
                        "time": 58.722312,
                        "endTime": 59.98822,
                        "type": "ground",
                        "id": 19
                    },
                    "key": "enter"
                }
            },
            {
                "time": "2019-06-27T23:21:00.951Z",
                "type": "START",
                "source": "hotkey",
                "_t": "17:21:00",
                "_end": "-",
                "data": {
                    "type": "ground",
                    "time": 60.432021
                }
            },
            {
                "time": "2019-06-27T23:21:02.218Z",
                "type": "END",
                "source": "hotkey:ctb",
                "_t": "17:21:02",
                "_end": "-",
                "data": {
                    "lbl": {
                        "time": 60.432021,
                        "endTime": 61.701619,
                        "type": "ground",
                        "id": 20
                    },
                    "key": "enter"
                }
            },
            {
                "time": "2019-06-27T23:21:02.691Z",
                "type": "START",
                "source": "hotkey",
                "_t": "17:21:02",
                "_end": "-",
                "data": {
                    "type": "ground",
                    "time": 62.178391
                }
            },
            {
                "time": "2019-06-27T23:21:04.074Z",
                "type": "END",
                "source": "hotkey:ctb",
                "_t": "17:21:04",
                "_end": "-",
                "data": {
                    "lbl": {
                        "time": 62.178391,
                        "endTime": 63.556177,
                        "type": "ground",
                        "id": 21
                    },
                    "key": "enter"
                }
            }
        ],
        "navigationEvents": [
            {
                "time": {
                    "start": "2019-06-27T23:19:50.513Z",
                    "end": "2019-06-27T23:19:50.545Z"
                },
                "type": "SCRUB",
                "source": "video:drag",
                "_t": "17:19:50",
                "_end": "17:19:50",
                "data": {
                    "to": 13.887497,
                    "from": 8.911196
                }
            },
            {
                "time": {
                    "start": "2019-06-27T23:19:53.833Z",
                    "end": "2019-06-27T23:19:53.865Z"
                },
                "type": "SCRUB",
                "source": "video:drag",
                "_t": "17:19:53",
                "_end": "17:19:53",
                "data": {
                    "to": 27.648168,
                    "from": 16.407958
                }
            },
            {
                "time": {
                    "start": "2019-06-27T23:19:54.603Z",
                    "end": "2019-06-27T23:19:54.685Z"
                },
                "type": "SCRUB",
                "source": "video:drag",
                "_t": "17:19:54",
                "_end": "17:19:54",
                "data": {
                    "to": 22.19463,
                    "from": 28.177876
                }
            },
            {
                "time": {
                    "start": "2019-06-27T23:20:08.426Z",
                    "end": "2019-06-27T23:20:08.455Z"
                },
                "type": "SCRUB",
                "source": "video:drag",
                "_t": "17:20:08",
                "_end": "17:20:08",
                "data": {
                    "to": 31.643201,
                    "from": 35.616376
                }
            },
            {
                "time": {
                    "start": "2019-06-27T23:20:09.074Z",
                    "end": "2019-06-27T23:20:10.950Z"
                },
                "type": "SCRUB",
                "source": "video:drag",
                "_t": "17:20:09",
                "_end": "17:20:10",
                "data": {
                    "to": 27.457928,
                    "from": 31.942492
                }
            },
            {
                "time": "2019-06-27T23:20:12.649Z",
                "type": "PAUSE",
                "source": "hotkey",
                "_t": "17:20:12",
                "_end": "-",
                "data": {
                    "key": "space"
                }
            },
            {
                "time": {
                    "start": "2019-06-27T23:19:36.870Z",
                    "end": "2019-06-27T23:20:14.936Z"
                },
                "type": "SCRUB",
                "source": "data:drag",
                "_t": "17:19:36",
                "_end": "17:20:14",
                "data": {
                    "time": 29.078709
                }
            },
            {
                "time": {
                    "start": "2019-06-27T23:19:36.870Z",
                    "end": "2019-06-27T23:20:16.414Z"
                },
                "type": "SCRUB",
                "source": "data:drag",
                "_t": "17:19:36",
                "_end": "17:20:16",
                "data": {
                    "time": 29.078709
                }
            },
            {
                "time": {
                    "start": "2019-06-27T23:19:36.870Z",
                    "end": "2019-06-27T23:20:17.471Z"
                },
                "type": "SCRUB",
                "source": "data:drag",
                "_t": "17:19:36",
                "_end": "17:20:17",
                "data": {
                    "time": 28.814662
                }
            },
            {
                "time": {
                    "start": "2019-06-27T23:19:36.870Z",
                    "end": "2019-06-27T23:20:18.572Z"
                },
                "type": "SCRUB",
                "source": "data:drag",
                "_t": "17:19:36",
                "_end": "17:20:18",
                "data": {
                    "time": 28.004519
                }
            },
            {
                "time": "2019-06-27T23:20:23.176Z",
                "type": "PLAY",
                "source": "hotkey",
                "_t": "17:20:23",
                "_end": "-",
                "data": {
                    "key": "space"
                }
            },
            {
                "time": "2019-06-27T23:20:24.855Z",
                "type": "PAUSE",
                "source": "hotkey",
                "_t": "17:20:24",
                "_end": "-",
                "data": {
                    "key": "space"
                }
            },
            {
                "time": "2019-06-27T23:20:27.463Z",
                "type": "PLAY",
                "source": "hotkey",
                "_t": "17:20:27",
                "_end": "-",
                "data": {
                    "key": "space"
                }
            },
            {
                "time": "2019-06-27T23:20:27.991Z",
                "type": "PAUSE",
                "source": "hotkey",
                "_t": "17:20:27",
                "_end": "-",
                "data": {
                    "key": "space"
                }
            },
            {
                "time": "2019-06-27T23:20:30.663Z",
                "type": "PLAY",
                "source": "hotkey",
                "_t": "17:20:30",
                "_end": "-",
                "data": {
                    "key": "space"
                }
            }
        ]
    }
}